webmail_domains/__init__.py
webmail_domains/webmail_domains.py
webmail_domains-0.22.dist-info/LICENSE
webmail_domains-0.22.dist-info/METADATA
webmail_domains-0.22.dist-info/WHEEL
webmail_domains-0.22.dist-info/top_level.txt
webmail_domains-0.22.dist-info/RECORD
