Metadata-Version: 2.1
Name: webmail-domains
Version: 0.22
Summary: A pretty thorough list of webmail domains!
Home-page: https://github.com/zevaverbach/Webmail-Domains
License: UNKNOWN
Platform: UNKNOWN
